Workbook

Sheet Calendrier
A1: Projet 4 : Analyse des données de vente et retours
A2: Calendrier des sprints aligné sur les dates de remise communiquées par le professeur
A4: Sprint | B4: Début | C4: Fin | D4: Semaines | E4: Objectif du sprint | F4: Livrable remis | G4: Date de remise | H4: Poids dans la note | I4: Nb de tâches | J4: Charge estimée (h)
A5: Sprint 0 | B5: 21 sept. 2026 | C5: 4 oct. 2026 | D5: 2 | E5: Cadrage, collecte et recherche des données (dont tables de dimension), planification Scrum | F5: Livrables 1 et 2 : phases du projet et tâches granulaires + présentation PowerPoint UA1 | G5: 5 oct. 2026 | H5: 0.2 | I5: =COUNTIF(Tâches!$D$2:$D$186,A5) -> 37 | J5: =SUMIF(Tâches!$D$2:$D$186,A5,Tâches!$G$2:$G$186) -> 55
A6: Sprint 1 | B6: 5 oct. 2026 | C6: 18 oct. 2026 | D6: 2 | E6: Consolidation des trimestres, modèle en flocon, pipeline ETL reproductible | I6: =COUNTIF(Tâches!$D$2:$D$186,A6) -> 27 | J6: =SUMIF(Tâches!$D$2:$D$186,A6,Tâches!$G$2:$G$186) -> 48.5
A7: Sprint 2 | B7: 19 oct. 2026 | C7: 1 nov. 2026 | D7: 2 | E7: Diagnostic de qualité et nettoyage des données | I7: =COUNTIF(Tâches!$D$2:$D$186,A7) -> 16 | J7: =SUMIF(Tâches!$D$2:$D$186,A7,Tâches!$G$2:$G$186) -> 25.5
A8: Sprint 3 | B8: 2 nov. 2026 | C8: 8 nov. 2026 | D8: 1 | E8: Transformation, variables dérivées, rapport de diagnostic | F8: Livrable 3 : diagnostic, nettoyage et transformation des données | G8: 9 nov. 2026 | H8: 0.25 | I8: =COUNTIF(Tâches!$D$2:$D$186,A8) -> 15 | J8: =SUMIF(Tâches!$D$2:$D$186,A8,Tâches!$G$2:$G$186) -> 22.5
A9: Sprint 4 | B9: 9 nov. 2026 | C9: 22 nov. 2026 | D9: 2 | E9: Analyse exploratoire Q1 à Q4, modèle prédictif des retours, tableau de bord Excel | I9: =COUNTIF(Tâches!$D$2:$D$186,A9) -> 40 | J9: =SUMIF(Tâches!$D$2:$D$186,A9,Tâches!$G$2:$G$186) -> 69
A10: Sprint 5 | B10: 23 nov. 2026 | C10: 6 déc. 2026 | D10: 2 | E10: Q5, modèles prédictifs (ventes, réponse aux promotions), simulation et optimisation des remises, Power BI, rapport et présentation | F10: Livrable 4 : analyse exploratoire, rapport et présentation des conclusions | G10: 7 déc. 2026 | H10: 0.35 | I10: =COUNTIF(Tâches!$D$2:$D$186,A10) -> 39 | J10: =SUMIF(Tâches!$D$2:$D$186,A10,Tâches!$G$2:$G$186) -> 75.5
A11: Sprint 6 | B11: 7 déc. 2026 | C11: 13 déc. 2026 | D11: 1 | E11: Analyse de sensibilité, plan promotionnel recommandé, recommandations opérationnelles et rapport final | F11: Livrable 5 : rapport final avec recommandations opérationnelles | G11: 14 déc. 2026 | H11: 0.2 | I11: =COUNTIF(Tâches!$D$2:$D$186,A11) -> 11 | J11: =SUMIF(Tâches!$D$2:$D$186,A11,Tâches!$G$2:$G$186) -> 19.5
A12: Total | D12: =SUM(D5:D11) -> 12 | H12: =SUM(H5:H11) -> 1 | I12: =SUM(I5:I11) -> 185 | J12: =SUM(J5:J11) -> 315.5
A14: Hypothèses :
A15: 1. La présentation PowerPoint UA1 correspond au premier jalon (phases et tâches granulaires, remise du 5 octobre). À ajuster si l'UA1 a une autre date.
A16: 2. Source vérifiée : les données fournies correspondent à FactSales de Contoso Retail DW (2008-2009, dates décalées de 12 ans). Utilisation des tables de dimension sous réserve de validation par le professeur. Les fichiers fournis couvrent 5 catégories de produits sur 8 et les trimestres 1 à 3. Depuis le 6 octobre, avec l'accord du professeur, le projet travaille sur les ventes complètes des 56 boutiques (8 catégories, 8 trimestres), extraites de Contoso.
A17: 3. Les remises tombent un lundi : chaque sprint se termine le dimanche précédent.
A18: 4. Outils : Python et ses bibliothèques pour l'ETL, l'analyse, la modélisation et l'optimisation, Excel (tableau de bord, Solveur) et Power BI (tableau de bord, what-if) pour la visualisation et la simulation, PowerPoint pour les présentations.
A19: Colonnes à remplir dans l'onglet Tâches (fond jaune) : Responsable et Statut.

Sheet Gantt
A1: Diagramme de Gantt du projet
A2: Une colonne par semaine (du lundi au dimanche). Barres vertes : sprints. Barres claires : épopées actives pendant le sprint. Losange orange : remise d'un livrable.
A4: Élément | B4: Début | C4: Fin | D4: Durée (sem.) | E4: Sem. 1 21 sept. | F4: Sem. 2 28 sept. | G4: Sem. 3 5 oct. | H4: Sem. 4 12 oct. | I4: Sem. 5 19 oct. | J4: Sem. 6 26 oct. | K4: Sem. 7 2 nov. | L4: Sem. 8 9 nov. | M4: Sem. 9 16 nov. | N4: Sem. 10 23 nov. | O4: Sem. 11 30 nov. | P4: Sem. 12 7 déc. | Q4: Sem. 13 14 déc.
A5: SPRINTS
A6: Sprint 0 · Cadrage, collecte et recherche de données | B6: 21 sept. 2026 | C6: 4 oct. 2026 | D6: 2 | E6: Sprint 0
A7: Sprint 1 · ETL, consolidation et modèle en flocon | B7: 5 oct. 2026 | C7: 18 oct. 2026 | D7: 2 | G7: Sprint 1
A8: Sprint 2 · Diagnostic de qualité et nettoyage | B8: 19 oct. 2026 | C8: 1 nov. 2026 | D8: 2 | I8: Sprint 2
A9: Sprint 3 · Transformation et rapport de diagnostic | B9: 2 nov. 2026 | C9: 8 nov. 2026 | D9: 1 | K9: Sprint 3
A10: Sprint 4 · Analyse Q1 à Q4, risque de retour, Excel | B10: 9 nov. 2026 | C10: 22 nov. 2026 | D10: 2 | L10: Sprint 4
A11: Sprint 5 · Q5, prédiction, simulation, optimisation, Power BI | B11: 23 nov. 2026 | C11: 6 déc. 2026 | D11: 2 | N11: Sprint 5
A12: Sprint 6 · Plan promotionnel et rapport final | B12: 7 déc. 2026 | C12: 13 déc. 2026 | D12: 1 | P12: Sprint 6
A13: ÉPOPÉES (sprints où l'épopée a des tâches)
A14: E0 Gestion de projet Scrum | B14: 21 sept. 2026 | C14: 13 déc. 2026 | D14: 12
A15: E1 Collecte et recherche de données | B15: 21 sept. 2026 | C15: 4 oct. 2026 | D15: 2
A16: E2 Intégration et modélisation (ETL) | B16: 21 sept. 2026 | C16: 18 oct. 2026 | D16: 4
A17: E3 Qualité et nettoyage | B17: 19 oct. 2026 | C17: 1 nov. 2026 | D17: 2
A18: E4 Transformation et variables dérivées | B18: 2 nov. 2026 | C18: 8 nov. 2026 | D18: 1
A19: E5 Analyse exploratoire (Q1 à Q5) | B19: 9 nov. 2026 | C19: 6 déc. 2026 | D19: 4
A20: E6 Modélisation prédictive | B20: 9 nov. 2026 | C20: 6 déc. 2026 | D20: 4
A21: E7 Tableaux de bord | B21: 9 nov. 2026 | C21: 6 déc. 2026 | D21: 4
A22: E8 Documentation et livrables | B22: 21 sept. 2026 | C22: 13 déc. 2026 | D22: 6
A23: E9 Analyse prescriptive | B23: 23 nov. 2026 | C23: 13 déc. 2026 | D23: 3
A24: LIVRABLES (remise le lundi)
A25: L1 et L2 + présentation UA1 (20 %) | B25: 5 oct. 2026 | C25: 5 oct. 2026 | G25: ◆
A26: L3 · Diagnostic, nettoyage, transformation (25 %) | B26: 9 nov. 2026 | C26: 9 nov. 2026 | L26: ◆
A27: L4 · Analyse, rapport et présentation (35 %) | B27: 7 déc. 2026 | C27: 7 déc. 2026 | P27: ◆
A28: L5 · Rapport final (20 %) | B28: 14 déc. 2026 | C28: 14 déc. 2026 | Q28: ◆
A29: Action de grâce (férié) | B29: 12 oct. 2026 | C29: 12 oct. 2026 | H29: férié

Sheet Épopées
A1: ID | B1: Épopée | C1: Objectif | D1: Nb de user stories | E1: Charge estimée (h)
A2: E0 | B2: Gestion de projet Scrum | C2: Organiser l'équipe, planifier et suivre les sprints | D2: =COUNTIF(Backlog!$C$2:$C$38,A2) -> 4 | E2: =SUMIF(Tâches!$C$2:$C$186,A2&" "&B2,Tâches!$G$2:$G$186) -> 29.5
A3: E1 | B3: Collecte et recherche de données | C3: Inventorier les données fournies, identifier les manques, collecter les tables de dimension et les données de contexte | D3: =COUNTIF(Backlog!$C$2:$C$38,A3) -> 4 | E3: =SUMIF(Tâches!$C$2:$C$186,A3&" "&B3,Tâches!$G$2:$G$186) -> 25
A4: E2 | B4: Intégration et modélisation (ETL) | C4: Consolider les trimestres et construire un modèle en flocon exploitable par Python, Excel et Power BI | D4: =COUNTIF(Backlog!$C$2:$C$38,A4) -> 5 | E4: =SUMIF(Tâches!$C$2:$C$186,A4&" "&B4,Tâches!$G$2:$G$186) -> 51
A5: E3 | B5: Qualité et nettoyage | C5: Diagnostiquer et corriger les anomalies | D5: =COUNTIF(Backlog!$C$2:$C$38,A5) -> 2 | E5: =SUMIF(Tâches!$C$2:$C$186,A5&" "&B5,Tâches!$G$2:$G$186) -> 23.5
A6: E4 | B6: Transformation et variables dérivées | C6: Créer les indicateurs de marge, de retour et de remise | D6: =COUNTIF(Backlog!$C$2:$C$38,A6) -> 2 | E6: =SUMIF(Tâches!$C$2:$C$186,A6&" "&B6,Tâches!$G$2:$G$186) -> 11
A7: E5 | B7: Analyse exploratoire (Q1 à Q5) | C7: Répondre aux questions de recherche en Python | D7: =COUNTIF(Backlog!$C$2:$C$38,A7) -> 8 | E7: =SUMIF(Tâches!$C$2:$C$186,A7&" "&B7,Tâches!$G$2:$G$186) -> 58.5
A8: E6 | B8: Modélisation prédictive | C8: Prévoir les ventes, le risque de retour et la réponse aux promotions | D8: =COUNTIF(Backlog!$C$2:$C$38,A8) -> 3 | E8: =SUMIF(Tâches!$C$2:$C$186,A8&" "&B8,Tâches!$G$2:$G$186) -> 29
A9: E7 | B9: Tableaux de bord | C9: Explorer d'autres modes de visualisation avec Excel et Power BI | D9: =COUNTIF(Backlog!$C$2:$C$38,A9) -> 2 | E9: =SUMIF(Tâches!$C$2:$C$186,A9&" "&B9,Tâches!$G$2:$G$186) -> 22
A10: E8 | B10: Documentation et livrables | C10: Rapports, présentations PowerPoint et remises | D10: =COUNTIF(Backlog!$C$2:$C$38,A10) -> 4 | E10: =SUMIF(Tâches!$C$2:$C$186,A10&" "&B10,Tâches!$G$2:$G$186) -> 41.5
A11: E9 | B11: Analyse prescriptive | C11: Simuler des scénarios de promotion et déterminer la politique de remise qui maximise la marge en valeur | D11: =COUNTIF(Backlog!$C$2:$C$38,A11) -> 3 | E11: =SUMIF(Tâches!$C$2:$C$186,A11&" "&B11,Tâches!$G$2:$G$186) -> 24.5
A12: Total | D12: =SUM(D2:D11) -> 37 | E12: =SUM(E2:E11) -> 315.5

Sheet Backlog
A1: ID US | B1: User story | C1: Épopée | D1: Sprint | E1: Critère d'acceptation | F1: Priorité (MoSCoW) | G1: Points | H1: Nb de tâches | I1: Charge estimée (h)
A2: US01 | B2: En tant qu'équipe, je veux un cadre Scrum et un espace de travail commun afin de coordonner le projet. | C2: E0 | D2: Sprint 0 | E2: Rôles attribués, projet Jira ou GitHub Projects créé, dépôt GitHub structuré, Definition of Done rédigée | F2: Must | G2: 3 | H2: =COUNTIF(Tâches!$B$2:$B$186,A2) -> 3 | I2: =SUMIF(Tâches!$B$2:$B$186,A2,Tâches!$G$2:$G$186) -> 3.5
A3: US02 | B3: En tant qu'analyste, je veux inventorier les données fournies afin de connaître leur périmètre réel. | C3: E1 | D3: Sprint 0 | E3: Les 6 trimestres fournis sont chargés, décrits et un dictionnaire de données initial existe | F3: Must | G3: 3 | H3: =COUNTIF(Tâches!$B$2:$B$186,A3) -> 3 | I3: =SUMIF(Tâches!$B$2:$B$186,A3,Tâches!$G$2:$G$186) -> 5
A4: US03 | B4: En tant qu'analyste, je veux identifier les données manquantes afin de mesurer leur impact sur les questions de recherche. | C4: E1 | D4: Sprint 0 | E4: Tableau des manques et de leur impact validé par l'équipe, demande envoyée au professeur | F4: Must | G4: 2 | H4: =COUNTIF(Tâches!$B$2:$B$186,A4) -> 3 | I4: =SUMIF(Tâches!$B$2:$B$186,A4,Tâches!$G$2:$G$186) -> 3.5
A5: US04 | B5: En tant qu'analyste, je veux collecter les tables de dimension et le jeu de données complet afin d'enrichir l'analyse. | C5: E1 | D5: Sprint 0 | E5: Source vérifiée (FactSales de Contoso, décalage de 12 ans), arborescence des clés établie, 8 tables retenues et justifiées, correspondance des clés mesurée | F5: Must | G5: 8 | H5: =COUNTIF(Tâches!$B$2:$B$186,A5) -> 10 | I5: =SUMIF(Tâches!$B$2:$B$186,A5,Tâches!$G$2:$G$186) -> 13
A6: US05 | B6: En tant qu'analyste, je veux collecter des données de contexte afin d'interpréter les tendances 2020 et 2021. | C6: E1 | D6: Sprint 0 | E6: Calendrier des jours fériés et périodes COVID-19 par pays disponibles et documentés | F6: Should | G6: 3 | H6: =COUNTIF(Tâches!$B$2:$B$186,A6) -> 2 | I6: =SUMIF(Tâches!$B$2:$B$186,A6,Tâches!$G$2:$G$186) -> 3.5
A7: US06 | B7: En tant que Product Owner, je veux découper le projet en phases et jalons afin de respecter le calendrier du cours (Livrable 1). | C7: E0 | D7: Sprint 0 | E7: Phases, jalons et diagramme de Gantt alignés sur les dates de remise | F7: Must | G7: 2 | H7: =COUNTIF(Tâches!$B$2:$B$186,A7) -> 2 | I7: =SUMIF(Tâches!$B$2:$B$186,A7,Tâches!$G$2:$G$186) -> 3.5
A8: US07 | B8: En tant que Product Owner, je veux un backlog de tâches granulaires, estimées et priorisées (Livrable 2). | C8: E0 | D8: Sprint 0 | E8: Toutes les tâches ont une estimation, une priorité, un sprint et un responsable, saisies dans l'outil | F8: Must | G8: 5 | H8: =COUNTIF(Tâches!$B$2:$B$186,A8) -> 4 | I8: =SUMIF(Tâches!$B$2:$B$186,A8,Tâches!$G$2:$G$186) -> 9.5
A9: US08 | B9: En tant qu'équipe, je veux présenter le cadrage du projet (présentation UA1). | C9: E8 | D9: Sprint 0 | E9: Présentation PowerPoint remise et répétée, chaque membre a une partie | F9: Must | G9: 3 | H9: =COUNTIF(Tâches!$B$2:$B$186,A9) -> 5 | I9: =SUMIF(Tâches!$B$2:$B$186,A9,Tâches!$G$2:$G$186) -> 7
A10: US09 | B10: En tant qu'analyste, je veux une table de faits unique consolidant tous les trimestres de ventes (6 fournis, puis 8 avec les ventes complètes). | C10: E2 | D10: Sprint 1 | E10: Nombre de lignes et totaux réconciliés avec les fichiers sources, aucun doublon non expliqué | F10: Must | G10: 5 | H10: =COUNTIF(Tâches!$B$2:$B$186,A10) -> 5 | I10: =SUMIF(Tâches!$B$2:$B$186,A10,Tâches!$G$2:$G$186) -> 8.5
A11: US10 | B11: En tant qu'analyste, je veux un modèle en flocon afin d'analyser les ventes par boutique, produit, promotion et date. | C11: E2 | D11: Sprint 1 | E11: Schéma documenté, dimensions jointes, taux de correspondance des clés supérieur ou égal au seuil fixé | F11: Must | G11: 8 | H11: =COUNTIF(Tâches!$B$2:$B$186,A11) -> 8 | I11: =SUMIF(Tâches!$B$2:$B$186,A11,Tâches!$G$2:$G$186) -> 12.5
A12: US11 | B12: En tant que membre de l'équipe, je veux un pipeline reproductible exécutable en une seule commande afin que chacun obtienne les mêmes résultats. | C12: E2 | D12: Sprint 1 | E12: run_pipeline.py exécute tous les notebooks dans l'ordre des dépendances (en parallèle quand ils sont indépendants), testé sur un poste vierge, README à jour | F12: Must | G12: 5 | H12: =COUNTIF(Tâches!$B$2:$B$186,A12) -> 5 | I12: =SUMIF(Tâches!$B$2:$B$186,A12,Tâches!$G$2:$G$186) -> 9.5
A13: US12 | B13: En tant qu'analyste, je veux un diagnostic complet de la qualité des données. | C13: E3 | D13: Sprint 2 | E13: Rapport d'anomalies chiffré (manquants, incohérences, valeurs aberrantes) | F13: Must | G13: 8 | H13: =COUNTIF(Tâches!$B$2:$B$186,A13) -> 11 | I13: =SUMIF(Tâches!$B$2:$B$186,A13,Tâches!$G$2:$G$186) -> 15.5
... A38: US37 | B38: En tant qu'analyste, je veux exploiter le détail des ventes en ligne (FactOnlineSales) afin de comprendre comment les remises sont appliquées (Q2). | C38: E5 | D38: Sprint 4 | E38: Agrégat mensuel du détail en ligne comparé aux ventes consolidées de la boutique en ligne, écart de remise expliqué, limite au seul canal en ligne écrite | F38: Could | G38: 5 | H38: =COUNTIF(Tâches!$B$2:$B$186,A38) -> 3 | I38: =SUMIF(Tâches!$B$2:$B$186,A38,Tâches!$G$2:$G$186) -> 4.5
A39: Total | G39: =SUM(G2:G38) -> 198 | H39: =SUM(H2:H38) -> 185 | I39: =SUM(I2:I38) -> 315.5
A41: Points : suite de Fibonacci (1, 2, 3, 5, 8). MoSCoW : Must = indispensable, Should = important, Could = souhaitable.

Sheet Tâches
A1: ID tâche | B1: ID US | C1: Épopée | D1: Sprint | E1: Tâche | F1: Outil | G1: Estimation (h) | H1: Responsable | I1: Statut | J1: Date de fin prévue
A2: T001 | B2: US01 | C2: E0 Gestion de projet Scrum | D2: Sprint 0 | E2: Définir les rôles : Product Owner, Scrum Master, développeurs | F2: Réunion | G2: 1 | H2: Toute l'équipe | I2: Terminé | J2: 4 oct. 2026
A3: T002 | B3: US01 | C3: E0 Gestion de projet Scrum | D3: Sprint 0 | E3: Créer le projet dans Jira ou GitHub Projects et inviter l'équipe | F3: Jira / GitHub Projects | G3: 1 | H3: Achraf | I3: Terminé | J3: 4 oct. 2026
A4: T003 | B4: US01 | C4: E0 Gestion de projet Scrum | D4: Sprint 0 | E4: Rédiger la Definition of Done et les conventions (nommage, branches, notebooks) | F4: Word / GitHub | G4: 1.5 | H4: Achraf | I4: Terminé | J4: 4 oct. 2026
A5: T004 | B5: US33 | C5: E2 Intégration et modélisation (ETL) | D5: Sprint 0 | E5: Définir l'arborescence du dépôt (data : raw, interim, clean, outputs ; notebooks par phase ; src ; tests ; dashboards ; reports) | F5: GitHub | G5: 1 | H5: Jean Robert | I5: Terminé | J5: 4 oct. 2026
A6: T005 | B6: US33 | C6: E2 Intégration et modélisation (ETL) | D6: Sprint 0 | E6: Créer les squelettes des 16 notebooks numérotés (00 à 15) avec leurs sections et un responsable par notebook | F6: Jupyter | G6: 1.5 | H6: Jean Robert | I6: Terminé | J6: 4 oct. 2026
A7: T006 | B7: US33 | C7: E2 Intégration et modélisation (ETL) | D7: Sprint 0 | E7: Configurer l'environnement (.venv, requirements.txt, config.py, .gitignore, README) | F7: Python / Git | G7: 1 | H7: Jean Robert | I7: Terminé | J7: 4 oct. 2026
A8: T007 | B8: US33 | C8: E2 Intégration et modélisation (ETL) | D8: Sprint 0 | E8: Créer la charte graphique commune (src/viz.py : couleurs, police, format des montants, enregistrement des figures) | F8: Python (matplotlib) | G8: 1 | H8: Jean Robert | I8: Terminé | J8: 4 oct. 2026
A9: T008 | B9: US02 | C9: E1 Collecte et recherche de données | D9: Sprint 0 | E9: Charger chaque fichier trimestriel et relever lignes, colonnes, types et période couverte (00_inventaire) | F9: Python (pandas) | G9: 2 | H9: Jean Robert | I9: Terminé | J9: 4 oct. 2026
A10: T009 | B10: US02 | C10: E1 Collecte et recherche de données | D10: Sprint 0 | E10: Vérifier la présence des 8 trimestres 2020 et 2021 et la continuité des dates (6 présents : T4 2020 et 2021 absents) | F10: Python (pandas) | G10: 1 | H10: Jean Robert | I10: Terminé | J10: 4 oct. 2026
A11: T010 | B11: US02 | C11: E1 Collecte et recherche de données | D11: Sprint 0 | E11: Rédiger le dictionnaire de données initial des 14 variables (dictionnaire_donnees.xlsx) | F11: Excel | G11: 2 | H11: Barnabé | I11: Terminé | J11: 4 oct. 2026
A12: T011 | B12: US03 | C12: E1 Collecte et recherche de données | D12: Sprint 0 | E12: Lister les dimensions et informations manquantes (boutique, produit, promotion, client, retours, stocks, charges) | F12: Excel | G12: 1.5 | H12: Barnabé | I12: Terminé | J12: 4 oct. 2026
A13: T012 | B13: US03 | C13: E1 Collecte et recherche de données | D13: Sprint 0 | E13: Évaluer l'impact de chaque manque sur les questions Q1 à Q5 | F13: Excel | G13: 1.5 | H13: Barnabé | I13: Terminé | J13: 4 oct. 2026
... A186: T185 | B186: US37 | C186: E5 Analyse exploratoire (Q1 à Q5) | D186: Sprint 4 | E186: Rédiger la synthèse et la limite (canal en ligne seulement) | F186: Word | G186: 1 | H186: À répartir | I186: À faire | J186: 22 nov. 2026
F187: Total | G187: =SUM(G2:G186) -> 315.5

Sheet Changements
A1: Date | B1: Élément | C1: Changement | D1: Raison | E1: Statut dans Jira
A2: 6 oct. 2026 | B2: Périmètre des données | C2: Passage des fichiers fournis (5 catégories, trimestres 1 à 3, 144 874 lignes) aux ventes complètes des 56 boutiques (8 catégories, 8 trimestres, 376 234 lignes) | D2: Seul périmètre comparable aux charges du plan stratégique ; les catégories absentes pèsent plus de la moitié du chiffre d'affaires ; fin d'année et promotion des Fêtes présentes | E2: Sans objet
A3: 6 oct. 2026 | B3: US34 (nouvelle, Must) | C3: Étendre les ventes au périmètre complet : 8 tâches T167 à T174, dont 7 déjà terminées | D3: Travail réalisé le 6 octobre, à tracer dans le backlog | E3: À créer
A4: 6 oct. 2026 | B4: US35 (nouvelle, Should) | C4: Rentabilité nette par boutique à partir des charges du plan stratégique : 5 tâches T175 à T179 | D4: Les charges par boutique existent dans Contoso et se rapprochent de nos ventes au cent près | E4: À créer
A5: 6 oct. 2026 | B5: US36 (nouvelle, Should) | C5: Dépenses de publicité face aux promotions : 3 tâches T180 à T182 | D5: Complète Q2 et Q5 | E5: À créer
A6: 6 oct. 2026 | B6: US37 (nouvelle, Could) | C6: Détail des ventes en ligne pour comprendre les remises : 3 tâches T183 à T185 | D6: Seule table transactionnelle de la base, limitée au canal en ligne | E6: À créer
A7: 6 oct. 2026 | B7: US28 | C7: Priorité Must -> Could (modèle prédictif du risque de retour) | D7: L'énoncé demande d'identifier les déterminants des retours (US19, US21) et des modèles prédictifs de ventes (US23), pas un modèle prédictif des retours | E7: À modifier
A8: 6 oct. 2026 | B8: US30 | C8: Priorité Must -> Could (simulation de scénarios what-if) | D8: La stratégie d'optimisation demandée est couverte par US31 | E8: À modifier
A9: 6 oct. 2026 | B9: US32 | C9: Priorité Must -> Could (analyse de sensibilité et calendrier promotionnel) | D9: Les recommandations opérationnelles demandées sont couvertes par US26 | E9: À modifier
A10: 6 oct. 2026 | B10: US09 | C10: Libellé : « tous les trimestres de ventes (6 fournis, puis 8) » | D10: Suite du changement de périmètre | E10: À modifier
A11: 6 oct. 2026 | B11: Nettoyage | C11: Nouvelle règle N6 : quantité remisée ramenée à la quantité vendue sur 386 lignes. Aucun montant modifié : le chiffre d'affaires reste égal à celui du plan stratégique | D11: Anomalie apparue avec la catégorie Home Appliances ; démarche détaillée dans 03_diagnostic et dans le L3 | E11: Sans objet
A13: Les documents remis le 5 octobre (L1, L2, présentation UA1) ne sont pas modifiés : cet onglet et le L3 expliquent les changements.
