Workbook

Sheet Calendrier
A1: Projet 4 : Analyse des données de vente et retours
A2: Calendrier des sprints aligné sur les dates de remise communiquées par le professeur
A4: Sprint | B4: Début | C4: Fin | D4: Semaines | E4: Objectif du sprint | F4: Livrable remis | G4: Date de remise | H4: Poids dans la note | I4: Nb de tâches | J4: Charge estimée (h)
A5: Sprint 0 | B5: 21 sept. 2026 | C5: 4 oct. 2026 | D5: 2 | E5: Cadrage, collecte et recherche des données (dont tables de dimension), planification Scrum | F5: Livrables 1 et 2 : phases du projet et tâches granulaires + présentation PowerPoint UA1 | G5: 5 oct. 2026 | H5: 0.2 | I5: =COUNTIF(Tâches!$D$2:$D$212,A5) | J5: =SUMIF(Tâches!$D$2:$D$212,A5,Tâches!$G$2:$G$212)
A6: Sprint 1 | B6: 5 oct. 2026 | C6: 18 oct. 2026 | D6: 2 | E6: ETL sur trois exercices (2019 à 2021) : consolidation des ventes, modèle en flocon, charges, stock et ventes en ligne détaillées, pipeline reproductible | I6: =COUNTIF(Tâches!$D$2:$D$212,A6) | J6: =SUMIF(Tâches!$D$2:$D$212,A6,Tâches!$G$2:$G$212)
A7: Sprint 2 | B7: 19 oct. 2026 | C7: 1 nov. 2026 | D7: 2 | E7: Diagnostic de qualité, nettoyage et variables dérivées ; analyse Q1 (06b_q1_chute_des_ventes, 06_q1_facteurs_rentabilite) | I7: =COUNTIF(Tâches!$D$2:$D$212,A7) | J7: =SUMIF(Tâches!$D$2:$D$212,A7,Tâches!$G$2:$G$212)
A8: Sprint 3 | B8: 2 nov. 2026 | C8: 8 nov. 2026 | D8: 1 | E8: Analyse Q2 à Q5 (07, 08, 09), rapport L3 + L4 et présentation UA2 | F8: Livrable 3 : diagnostic, nettoyage et transformation, avec l'analyse exploratoire de Q1 à Q5 faite en avance (présentation UA2) | G8: 9 nov. 2026 | H8: 0.25 | I8: =COUNTIF(Tâches!$D$2:$D$212,A8) | J8: =SUMIF(Tâches!$D$2:$D$212,A8,Tâches!$G$2:$G$212)
A9: Sprint 4 | B9: 9 nov. 2026 | C9: 22 nov. 2026 | D9: 2 | E9: Prédictif et exploratoire : 10_prevision_ventes (régression), 11_grands_comptes (classification), 12_typologie_magasins (clustering) | I9: =COUNTIF(Tâches!$D$2:$D$212,A9) | J9: =SUMIF(Tâches!$D$2:$D$212,A9,Tâches!$G$2:$G$212)
A10: Sprint 5 | B10: 23 nov. 2026 | C10: 6 déc. 2026 | D10: 2 | E10: Prescriptif : 13_priorites_renouvellement (optimisation sous budget d'achat), 14_simulateur (recherche aléatoire et Monte-Carlo) ; application Streamlit (tableau de bord et simulateur), Power BI en option (Could) ; rapport et présentation UA3 | F10: Livrable 4 : modèles prédictifs et prescriptifs, application Streamlit, rapport et présentation (l'analyse exploratoire est remise avec le livrable 3) | G10: 7 déc. 2026 | H10: 0.35 | I10: =COUNTIF(Tâches!$D$2:$D$212,A10) | J10: =SUMIF(Tâches!$D$2:$D$212,A10,Tâches!$G$2:$G$212)
A11: Sprint 6 | B11: 7 déc. 2026 | C11: 13 déc. 2026 | D11: 1 | E11: Recommandations opérationnelles, plan d'essais des leviers incertains (section du rapport), rapport final | F11: Livrable 5 : rapport final avec recommandations opérationnelles | G11: 14 déc. 2026 | H11: 0.2 | I11: =COUNTIF(Tâches!$D$2:$D$212,A11) | J11: =SUMIF(Tâches!$D$2:$D$212,A11,Tâches!$G$2:$G$212)
A12: Total | D12: =SUM(D5:D11) | H12: =SUM(H5:H11) | I12: =SUM(I5:I11) | J12: =SUM(J5:J11)
A14: Hypothèses :
A15: 1. La présentation PowerPoint UA1 correspond au premier jalon (phases et tâches granulaires, remise du 5 octobre). À ajuster si l'UA1 a une autre date.
A16: 2. Source vérifiée : les données fournies correspondent à FactSales de Contoso Retail DW (2008-2009, dates décalées de 12 ans). Utilisation des tables de dimension sous réserve de validation par le professeur. Les fichiers fournis couvrent 5 catégories de produits sur 8 et les trimestres 1 à 3. Depuis le 6 octobre, avec l'accord du professeur, le projet travaille sur les ventes complètes des 56 boutiques (8 catégories, 8 trimestres), extraites de Contoso.
A17: 3. Les remises tombent un lundi : chaque sprint se termine le dimanche précédent.
A18: 4. Outils : Python et ses bibliothèques pour l'ETL, l'analyse, la modélisation et l'optimisation ; Streamlit pour le tableau de bord et le simulateur ; Power BI en option ; PowerPoint pour les présentations.
A19: Colonnes à remplir dans l'onglet Tâches (fond jaune) : Responsable et Statut.
A20: Mise à jour du 7 oct. 2026 : les analyses Q1 à Q5 (notebooks 06 à 09) sont terminées en avance. Les sprints et les dates de remise ne changent pas. Le contenu des sprints 5 et 6 est réorienté (onglet Changements).
A21: Mise à jour du 8 oct. 2026 : planning revu. L'ETL et l'analyse (Q1 à Q5) restent planifiés jusqu'au 8 novembre, alignés sur la remise du livrable 3 (présentation UA2), même si l'équipe a de l'avance. Les sprints 4 à 6 portent sur les notebooks 10 à 14 et l'application Streamlit. Les dates de remise ne changent pas. Les user stories et les tâches seront mises à jour au fil de l'avancement.

Sheet Gantt
A1: Diagramme de Gantt du projet
A2: Une colonne par semaine (du lundi au dimanche). Barres vertes : sprints. Barres claires : épopées actives pendant le sprint. Losange orange : remise d'un livrable.
A4: Élément | B4: Début | C4: Fin | D4: Durée (sem.) | E4: Sem. 1 21 sept. | F4: Sem. 2 28 sept. | G4: Sem. 3 5 oct. | H4: Sem. 4 12 oct. | I4: Sem. 5 19 oct. | J4: Sem. 6 26 oct. | K4: Sem. 7 2 nov. | L4: Sem. 8 9 nov. | M4: Sem. 9 16 nov. | N4: Sem. 10 23 nov. | O4: Sem. 11 30 nov. | P4: Sem. 12 7 déc. | Q4: Sem. 13 14 déc.
A5: SPRINTS
A6: Sprint 0 · Cadrage, collecte et recherche de données | B6: 21 sept. 2026 | C6: 4 oct. 2026 | D6: 2 | E6: Sprint 0
A7: Sprint 1 · ETL sur trois exercices et modèle de données | B7: 5 oct. 2026 | C7: 18 oct. 2026 | D7: 2 | G7: Sprint 1
A8: Sprint 2 · Diagnostic, nettoyage, variables et analyse Q1 | B8: 19 oct. 2026 | C8: 1 nov. 2026 | D8: 2 | I8: Sprint 2
A9: Sprint 3 · Analyse Q2 à Q5, rapport et présentation UA2 | B9: 2 nov. 2026 | C9: 8 nov. 2026 | D9: 1 | K9: Sprint 3
A10: Sprint 4 · Prévision, grands comptes, typologie (10, 11, 12) | B10: 9 nov. 2026 | C10: 22 nov. 2026 | D10: 2 | L10: Sprint 4
A11: Sprint 5 · Renouvellement, simulateur, Streamlit (13, 14), rapport UA3 | B11: 23 nov. 2026 | C11: 6 déc. 2026 | D11: 2 | N11: Sprint 5
A12: Sprint 6 · Recommandations, plan d'essais et rapport final | B12: 7 déc. 2026 | C12: 13 déc. 2026 | D12: 1 | P12: Sprint 6
A13: ÉPOPÉES (sprints où l'épopée a des tâches)
A14: E0 Gestion de projet Scrum | B14: 21 sept. 2026 | C14: 13 déc. 2026 | D14: 12
A15: E1 Collecte et recherche de données | B15: 21 sept. 2026 | C15: 4 oct. 2026 | D15: 2
A16: E2 Intégration et modélisation (ETL) | B16: 21 sept. 2026 | C16: 18 oct. 2026 | D16: 4
A17: E3 Qualité et nettoyage | B17: 19 oct. 2026 | C17: 1 nov. 2026 | D17: 2
A18: E4 Transformation et variables dérivées | B18: 2 nov. 2026 | C18: 8 nov. 2026 | D18: 1
A19: E5 Analyse exploratoire (Q1 à Q5) | B19: 9 nov. 2026 | C19: 6 déc. 2026 | D19: 4
A20: E6 Modélisation prédictive | B20: 9 nov. 2026 | C20: 6 déc. 2026 | D20: 4
A21: E7 Tableaux de bord | B21: 9 nov. 2026 | C21: 6 déc. 2026 | D21: 4
A22: E8 Documentation et livrables | B22: 21 sept. 2026 | C22: 13 déc. 2026 | D22: 6
A23: E9 Analyse prescriptive | B23: 23 nov. 2026 | C23: 13 déc. 2026 | D23: 3
A24: LIVRABLES (remise le lundi)
A25: L1 et L2 + présentation UA1 (20 %) | B25: 5 oct. 2026 | C25: 5 oct. 2026 | G25: ◆
A26: L3 · Diagnostic, nettoyage, transformation et analyse exploratoire, présentation UA2 (25 %) | B26: 9 nov. 2026 | C26: 9 nov. 2026 | L26: ◆
A27: L4 · Prédictif, prescriptif, Streamlit, rapport et présentation UA3 (35 %) | B27: 7 déc. 2026 | C27: 7 déc. 2026 | P27: ◆
A28: L5 · Rapport final (20 %) | B28: 14 déc. 2026 | C28: 14 déc. 2026 | Q28: ◆
A29: Action de grâce (férié) | B29: 12 oct. 2026 | C29: 12 oct. 2026 | H29: férié

Sheet Épopées
A1: ID | B1: Épopée | C1: Objectif | D1: Nb de user stories | E1: Charge estimée (h)
A2: E0 | B2: Gestion de projet Scrum | C2: Organiser l'équipe, planifier et suivre les sprints | D2: =COUNTIF(Backlog!$C$2:$C$43,A2) | E2: =SUMIF(Tâches!$C$2:$C$212,A2&" "&B2,Tâches!$G$2:$G$212)
A3: E1 | B3: Collecte et recherche de données | C3: Inventorier les données fournies, identifier les manques, collecter les tables de dimension et les données de contexte | D3: =COUNTIF(Backlog!$C$2:$C$43,A3) | E3: =SUMIF(Tâches!$C$2:$C$212,A3&" "&B3,Tâches!$G$2:$G$212)
A4: E2 | B4: Intégration et modélisation (ETL) | C4: Consolider les trimestres et construire un modèle en flocon exploitable par Python, Excel et Power BI | D4: =COUNTIF(Backlog!$C$2:$C$43,A4) | E4: =SUMIF(Tâches!$C$2:$C$212,A4&" "&B4,Tâches!$G$2:$G$212)
A5: E3 | B5: Qualité et nettoyage | C5: Diagnostiquer et corriger les anomalies | D5: =COUNTIF(Backlog!$C$2:$C$43,A5) | E5: =SUMIF(Tâches!$C$2:$C$212,A5&" "&B5,Tâches!$G$2:$G$212)
A6: E4 | B6: Transformation et variables dérivées | C6: Créer les indicateurs de marge, de retour et de remise | D6: =COUNTIF(Backlog!$C$2:$C$43,A6) | E6: =SUMIF(Tâches!$C$2:$C$212,A6&" "&B6,Tâches!$G$2:$G$212)
A7: E5 | B7: Analyse exploratoire (Q1 à Q5) | C7: Répondre aux questions de recherche en Python | D7: =COUNTIF(Backlog!$C$2:$C$43,A7) | E7: =SUMIF(Tâches!$C$2:$C$212,A7&" "&B7,Tâches!$G$2:$G$212)
A8: E6 | B8: Modélisation prédictive | C8: Prévoir les ventes par l'âge du catalogue, modéliser les charges selon les ventes, établir une typologie des magasins | D8: =COUNTIF(Backlog!$C$2:$C$43,A8) | E8: =SUMIF(Tâches!$C$2:$C$212,A8&" "&B8,Tâches!$G$2:$G$212)
A9: E7 | B9: Tableaux de bord | C9: Explorer d'autres modes de visualisation avec Excel, Power BI et une application Streamlit | D9: =COUNTIF(Backlog!$C$2:$C$43,A9) | E9: =SUMIF(Tâches!$C$2:$C$212,A9&" "&B9,Tâches!$G$2:$G$212)
A10: E8 | B10: Documentation et livrables | C10: Rapports, présentations PowerPoint et remises | D10: =COUNTIF(Backlog!$C$2:$C$43,A10) | E10: =SUMIF(Tâches!$C$2:$C$212,A10&" "&B10,Tâches!$G$2:$G$212)
A11: E9 | B11: Analyse prescriptive | C11: Simuler des scénarios de rentabilité, prioriser le renouvellement du catalogue et planifier les essais des leviers incertains | D11: =COUNTIF(Backlog!$C$2:$C$43,A11) | E11: =SUMIF(Tâches!$C$2:$C$212,A11&" "&B11,Tâches!$G$2:$G$212)
A12: Total | D12: =SUM(D2:D11) | E12: =SUM(E2:E11)

Sheet Backlog
A1: ID US | B1: User story | C1: Épopée | D1: Sprint | E1: Critère d'acceptation | F1: Priorité (MoSCoW) | G1: Points | H1: Nb de tâches | I1: Charge estimée (h) | J1: Tâches terminées | K1: État au 7 oct. 2026
A2: US01 | B2: En tant qu'équipe, je veux un cadre Scrum et un espace de travail commun afin de coordonner le projet. | C2: E0 | D2: Sprint 0 | E2: Rôles attribués, projet Jira ou GitHub Projects créé, dépôt GitHub structuré, Definition of Done rédigée | F2: Must | G2: 3 | H2: =COUNTIF(Tâches!$B$2:$B$212,A2) | I2: =SUMIF(Tâches!$B$2:$B$212,A2,Tâches!$G$2:$G$212) | J2: =COUNTIFS(Tâches!$B$2:$B$212,A2,Tâches!$I$2:$I$212,"Terminé") | K2: =IF(F2="Won't","Abandonnée",IF(J2+COUNTIFS(Tâches!$B$2:$B$212,A2,Tâches!$I$2:$I$212,"En cours")=0,"À faire",IF(J2+COUNTIFS(Tâches!$B$2:$B$212,A2,Tâches!$I$2:$I$212,"Écartée")>=H2,"Terminée","En cours")))
A3: US02 | B3: En tant qu'analyste, je veux inventorier les données fournies afin de connaître leur périmètre réel. | C3: E1 | D3: Sprint 0 | E3: Les 6 trimestres fournis sont chargés, décrits et un dictionnaire de données initial existe | F3: Must | G3: 3 | H3: =COUNTIF(Tâches!$B$2:$B$212,A3) | I3: =SUMIF(Tâches!$B$2:$B$212,A3,Tâches!$G$2:$G$212) | J3: =COUNTIFS(Tâches!$B$2:$B$212,A3,Tâches!$I$2:$I$212,"Terminé") | K3: =IF(F3="Won't","Abandonnée",IF(J3+COUNTIFS(Tâches!$B$2:$B$212,A3,Tâches!$I$2:$I$212,"En cours")=0,"À faire",IF(J3+COUNTIFS(Tâches!$B$2:$B$212,A3,Tâches!$I$2:$I$212,"Écartée")>=H3,"Terminée","En cours")))
A4: US03 | B4: En tant qu'analyste, je veux identifier les données manquantes afin de mesurer leur impact sur les questions de recherche. | C4: E1 | D4: Sprint 0 | E4: Tableau des manques et de leur impact validé par l'équipe, demande envoyée au professeur | F4: Must | G4: 2 | H4: =COUNTIF(Tâches!$B$2:$B$212,A4) | I4: =SUMIF(Tâches!$B$2:$B$212,A4,Tâches!$G$2:$G$212) | J4: =COUNTIFS(Tâches!$B$2:$B$212,A4,Tâches!$I$2:$I$212,"Terminé") | K4: =IF(F4="Won't","Abandonnée",IF(J4+COUNTIFS(Tâches!$B$2:$B$212,A4,Tâches!$I$2:$I$212,"En cours")=0,"À faire",IF(J4+COUNTIFS(Tâches!$B$2:$B$212,A4,Tâches!$I$2:$I$212,"Écartée")>=H4,"Terminée","En cours")))
A5: US04 | B5: En tant qu'analyste, je veux collecter les tables de dimension et le jeu de données complet afin d'enrichir l'analyse. | C5: E1 | D5: Sprint 0 | E5: Source vérifiée (FactSales de Contoso, décalage de 12 ans), arborescence des clés établie, 8 tables retenues et justifiées, correspondance des clés mesurée | F5: Must | G5: 8 | H5: =COUNTIF(Tâches!$B$2:$B$212,A5) | I5: =SUMIF(Tâches!$B$2:$B$212,A5,Tâches!$G$2:$G$212) | J5: =COUNTIFS(Tâches!$B$2:$B$212,A5,Tâches!$I$2:$I$212,"Terminé") | K5: =IF(F5="Won't","Abandonnée",IF(J5+COUNTIFS(Tâches!$B$2:$B$212,A5,Tâches!$I$2:$I$212,"En cours")=0,"À faire",IF(J5+COUNTIFS(Tâches!$B$2:$B$212,A5,Tâches!$I$2:$I$212,"Écartée")>=H5,"Terminée","En cours")))
A6: US05 | B6: En tant qu'analyste, je veux collecter des données de contexte afin d'interpréter les tendances 2020 et 2021. | C6: E1 | D6: Sprint 0 | E6: Calendrier des jours fériés et périodes COVID-19 par pays disponibles et documentés | F6: Should | G6: 3 | H6: =COUNTIF(Tâches!$B$2:$B$212,A6) | I6: =SUMIF(Tâches!$B$2:$B$212,A6,Tâches!$G$2:$G$212) | J6: =COUNTIFS(Tâches!$B$2:$B$212,A6,Tâches!$I$2:$I$212,"Terminé") | K6: =IF(F6="Won't","Abandonnée",IF(J6+COUNTIFS(Tâches!$B$2:$B$212,A6,Tâches!$I$2:$I$212,"En cours")=0,"À faire",IF(J6+COUNTIFS(Tâches!$B$2:$B$212,A6,Tâches!$I$2:$I$212,"Écartée")>=H6,"Terminée","En cours")))
A7: US06 | B7: En tant que Product Owner, je veux découper le projet en phases et jalons afin de respecter le calendrier du cours (Livrable 1). | C7: E0 | D7: Sprint 0 | E7: Phases, jalons et diagramme de Gantt alignés sur les dates de remise | F7: Must | G7: 2 | H7: =COUNTIF(Tâches!$B$2:$B$212,A7) | I7: =SUMIF(Tâches!$B$2:$B$212,A7,Tâches!$G$2:$G$212) | J7: =COUNTIFS(Tâches!$B$2:$B$212,A7,Tâches!$I$2:$I$212,"Terminé") | K7: =IF(F7="Won't","Abandonnée",IF(J7+COUNTIFS(Tâches!$B$2:$B$212,A7,Tâches!$I$2:$I$212,"En cours")=0,"À faire",IF(J7+COUNTIFS(Tâches!$B$2:$B$212,A7,Tâches!$I$2:$I$212,"Écartée")>=H7,"Terminée","En cours")))
A8: US07 | B8: En tant que Product Owner, je veux un backlog de tâches granulaires, estimées et priorisées (Livrable 2). | C8: E0 | D8: Sprint 0 | E8: Toutes les tâches ont une estimation, une priorité, un sprint et un responsable, saisies dans l'outil | F8: Must | G8: 5 | H8: =COUNTIF(Tâches!$B$2:$B$212,A8) | I8: =SUMIF(Tâches!$B$2:$B$212,A8,Tâches!$G$2:$G$212) | J8: =COUNTIFS(Tâches!$B$2:$B$212,A8,Tâches!$I$2:$I$212,"Terminé") | K8: =IF(F8="Won't","Abandonnée",IF(J8+COUNTIFS(Tâches!$B$2:$B$212,A8,Tâches!$I$2:$I$212,"En cours")=0,"À faire",IF(J8+COUNTIFS(Tâches!$B$2:$B$212,A8,Tâches!$I$2:$I$212,"Écartée")>=H8,"Terminée","En cours")))
A9: US08 | B9: En tant qu'équipe, je veux présenter le cadrage du projet (présentation UA1). | C9: E8 | D9: Sprint 0 | E9: Présentation PowerPoint remise et répétée, chaque membre a une partie | F9: Must | G9: 3 | H9: =COUNTIF(Tâches!$B$2:$B$212,A9) | I9: =SUMIF(Tâches!$B$2:$B$212,A9,Tâches!$G$2:$G$212) | J9: =COUNTIFS(Tâches!$B$2:$B$212,A9,Tâches!$I$2:$I$212,"Terminé") | K9: =IF(F9="Won't","Abandonnée",IF(J9+COUNTIFS(Tâches!$B$2:$B$212,A9,Tâches!$I$2:$I$212,"En cours")=0,"À faire",IF(J9+COUNTIFS(Tâches!$B$2:$B$212,A9,Tâches!$I$2:$I$212,"Écartée")>=H9,"Terminée","En cours")))
A10: US09 | B10: En tant qu'analyste, je veux une table de faits unique consolidant tous les trimestres de ventes (6 fournis, puis 8 avec les ventes complètes). | C10: E2 | D10: Sprint 1 | E10: Nombre de lignes et totaux réconciliés avec les fichiers sources, aucun doublon non expliqué | F10: Must | G10: 5 | H10: =COUNTIF(Tâches!$B$2:$B$212,A10) | I10: =SUMIF(Tâches!$B$2:$B$212,A10,Tâches!$G$2:$G$212) | J10: =COUNTIFS(Tâches!$B$2:$B$212,A10,Tâches!$I$2:$I$212,"Terminé") | K10: =IF(F10="Won't","Abandonnée",IF(J10+COUNTIFS(Tâches!$B$2:$B$212,A10,Tâches!$I$2:$I$212,"En cours")=0,"À faire",IF(J10+COUNTIFS(Tâches!$B$2:$B$212,A10,Tâches!$I$2:$I$212,"Écartée")>=H10,"Terminée","En cours")))
A11: US10 | B11: En tant qu'analyste, je veux un modèle en flocon afin d'analyser les ventes par boutique, produit, promotion et date. | C11: E2 | D11: Sprint 1 | E11: Schéma documenté, dimensions jointes, taux de correspondance des clés supérieur ou égal au seuil fixé | F11: Must | G11: 8 | H11: =COUNTIF(Tâches!$B$2:$B$212,A11) | I11: =SUMIF(Tâches!$B$2:$B$212,A11,Tâches!$G$2:$G$212) | J11: =COUNTIFS(Tâches!$B$2:$B$212,A11,Tâches!$I$2:$I$212,"Terminé") | K11: =IF(F11="Won't","Abandonnée",IF(J11+COUNTIFS(Tâches!$B$2:$B$212,A11,Tâches!$I$2:$I$212,"En cours")=0,"À faire",IF(J11+COUNTIFS(Tâches!$B$2:$B$212,A11,Tâches!$I$2:$I$212,"Écartée")>=H11,"Terminée","En cours")))
A12: US11 | B12: En tant que membre de l'équipe, je veux un pipeline reproductible exécutable en une seule commande afin que chacun obtienne les mêmes résultats. | C12: E2 | D12: Sprint 1 | E12: run_pipeline.py exécute tous les notebooks dans l'ordre des dépendances (en parallèle quand ils sont indépendants), testé sur un poste vierge, README à jour | F12: Must | G12: 5 | H12: =COUNTIF(Tâches!$B$2:$B$212,A12) | I12: =SUMIF(Tâches!$B$2:$B$212,A12,Tâches!$G$2:$G$212) | J12: =COUNTIFS(Tâches!$B$2:$B$212,A12,Tâches!$I$2:$I$212,"Terminé") | K12: =IF(F12="Won't","Abandonnée",IF(J12+COUNTIFS(Tâches!$B$2:$B$212,A12,Tâches!$I$2:$I$212,"En cours")=0,"À faire",IF(J12+COUNTIFS(Tâches!$B$2:$B$212,A12,Tâches!$I$2:$I$212,"Écartée")>=H12,"Terminée","En cours")))
A13: US12 | B13: En tant qu'analyste, je veux un diagnostic complet de la qualité des données. | C13: E3 | D13: Sprint 2 | E13: Rapport d'anomalies chiffré (manquants, incohérences, valeurs aberrantes) | F13: Must | G13: 8 | H13: =COUNTIF(Tâches!$B$2:$B$212,A13) | I13: =SUMIF(Tâches!$B$2:$B$212,A13,Tâches!$G$2:$G$212) | J13: =COUNTIFS(Tâches!$B$2:$B$212,A13,Tâches!$I$2:$I$212,"Terminé") | K13: =IF(F13="Won't","Abandonnée",IF(J13+COUNTIFS(Tâches!$B$2:$B$212,A13,Tâches!$I$2:$I$212,"En cours")=0,"À faire",IF(J13+COUNTIFS(Tâches!$B$2:$B$212,A13,Tâches!$I$2:$I$212,"Écartée")>=H13,"Terminée","En cours")))
... A43: US42 | B43: En tant qu'utilisateur métier, je veux une application Streamlit reprenant les quatre pages du tableau de bord afin de les consulter sans Power BI. | C43: E7 | D43: Sprint 5 | E43: Application lancée en une commande, 4 pages (vue d'ensemble, catalogue, magasins et charges, simulateur), chiffres identiques à ceux des notebooks | F43: Should | G43: 8 | H43: =COUNTIF(Tâches!$B$2:$B$212,A43) | I43: =SUMIF(Tâches!$B$2:$B$212,A43,Tâches!$G$2:$G$212) | J43: =COUNTIFS(Tâches!$B$2:$B$212,A43,Tâches!$I$2:$I$212,"Terminé") | K43: =IF(F43="Won't","Abandonnée",IF(J43+COUNTIFS(Tâches!$B$2:$B$212,A43,Tâches!$I$2:$I$212,"En cours")=0,"À faire",IF(J43+COUNTIFS(Tâches!$B$2:$B$212,A43,Tâches!$I$2:$I$212,"Écartée")>=H43,"Terminée","En cours")))
A44: Total | G44: =SUM(G2:G43) | H44: =SUM(H2:H43) | I44: =SUM(I2:I43) | J44: =SUM(J2:J43)
A46: Points : suite de Fibonacci (1, 2, 3, 5, 8). MoSCoW : Must = indispensable, Should = important, Could = souhaitable. Won't = écarté (voir l'onglet Changements).
A47: Colonnes J et K : calculées à partir de l'onglet Tâches. Terminée = toutes les tâches non écartées sont terminées. Abandonnée = priorité Won't.

Sheet Tâches
A1: ID tâche | B1: ID US | C1: Épopée | D1: Sprint | E1: Tâche | F1: Outil | G1: Estimation (h) | H1: Responsable | I1: Statut | J1: Date de fin prévue | K1: Date de fin réelle | L1: Commentaire (mise à jour du 7 oct. 2026)
A2: T001 | B2: US01 | C2: E0 Gestion de projet Scrum | D2: Sprint 0 | E2: Définir les rôles : Product Owner, Scrum Master, développeurs | F2: Réunion | G2: 1 | H2: Toute l'équipe | I2: Terminé | J2: 4 oct. 2026
A3: T002 | B3: US01 | C3: E0 Gestion de projet Scrum | D3: Sprint 0 | E3: Créer le projet dans Jira ou GitHub Projects et inviter l'équipe | F3: Jira / GitHub Projects | G3: 1 | H3: Achraf | I3: Terminé | J3: 4 oct. 2026
A4: T003 | B4: US01 | C4: E0 Gestion de projet Scrum | D4: Sprint 0 | E4: Rédiger la Definition of Done et les conventions (nommage, branches, notebooks) | F4: Word / GitHub | G4: 1.5 | H4: Achraf | I4: Terminé | J4: 4 oct. 2026
A5: T004 | B5: US33 | C5: E2 Intégration et modélisation (ETL) | D5: Sprint 0 | E5: Définir l'arborescence du dépôt (data : raw, interim, clean, outputs ; notebooks par phase ; src ; tests ; dashboards ; reports) | F5: GitHub | G5: 1 | H5: Yacine | I5: Terminé | J5: 4 oct. 2026
A6: T005 | B6: US33 | C6: E2 Intégration et modélisation (ETL) | D6: Sprint 0 | E6: Créer les squelettes des 16 notebooks numérotés (00 à 15) avec leurs sections et un responsable par notebook | F6: Jupyter | G6: 1.5 | H6: Yacine | I6: Terminé | J6: 4 oct. 2026
A7: T006 | B7: US33 | C7: E2 Intégration et modélisation (ETL) | D7: Sprint 0 | E7: Configurer l'environnement (.venv, requirements.txt, config.py, .gitignore, README) | F7: Python / Git | G7: 1 | H7: Yacine | I7: Terminé | J7: 4 oct. 2026
A8: T007 | B8: US33 | C8: E2 Intégration et modélisation (ETL) | D8: Sprint 0 | E8: Créer la charte graphique commune (src/viz.py : couleurs, police, format des montants, enregistrement des figures) | F8: Python (matplotlib) | G8: 1 | H8: Yacine | I8: Terminé | J8: 4 oct. 2026
A9: T008 | B9: US02 | C9: E1 Collecte et recherche de données | D9: Sprint 0 | E9: Charger chaque fichier trimestriel et relever lignes, colonnes, types et période couverte (00_inventaire) | F9: Python (pandas) | G9: 2 | H9: Yacine | I9: Terminé | J9: 4 oct. 2026
A10: T009 | B10: US02 | C10: E1 Collecte et recherche de données | D10: Sprint 0 | E10: Vérifier la présence des 8 trimestres 2020 et 2021 et la continuité des dates (6 présents : T4 2020 et 2021 absents) | F10: Python (pandas) | G10: 1 | H10: Yacine | I10: Terminé | J10: 4 oct. 2026
A11: T010 | B11: US02 | C11: E1 Collecte et recherche de données | D11: Sprint 0 | E11: Rédiger le dictionnaire de données initial des 14 variables (dictionnaire_donnees.xlsx) | F11: Excel | G11: 2 | H11: Barnabé | I11: Terminé | J11: 4 oct. 2026
A12: T011 | B12: US03 | C12: E1 Collecte et recherche de données | D12: Sprint 0 | E12: Lister les dimensions et informations manquantes (boutique, produit, promotion, client, retours, stocks, charges) | F12: Excel | G12: 1.5 | H12: Barnabé | I12: Terminé | J12: 4 oct. 2026
A13: T012 | B13: US03 | C13: E1 Collecte et recherche de données | D13: Sprint 0 | E13: Évaluer l'impact de chaque manque sur les questions Q1 à Q5 | F13: Excel | G13: 1.5 | H13: Barnabé | I13: Terminé | J13: 4 oct. 2026
... A38: T037 | B38: US27 | C38: E0 Gestion de projet Scrum | D38: Sprint 0 | E38: Sprint 0 : planification, revue et rétrospective | F38: Réunion | G38: 2 | H38: Achraf | I38: Terminé | J38: 4 oct. 2026
A39: T038 | B39: US09 | C39: E2 Intégration et modélisation (ETL) | D39: Sprint 1 | E39: Écrire le script de chargement des fichiers de ventes (data/raw/contoso/Sales) | F39: Python (pandas) | G39: 2 | H39: Yacine | I39: Terminé | J39: 18 oct. 2026 | K39: 6 oct. 2026 | L39: Notebook 01_etl, exécuté sur les ventes complètes
A40: T039 | B40: US09 | C40: E2 Intégration et modélisation (ETL) | D40: Sprint 1 | E40: Harmoniser noms de colonnes, types et dates, convertir les montants texte (« $1,062.60 ») en nombres | F40: Python (pandas) | G40: 2 | H40: Yacine | I40: Terminé | J40: 18 oct. 2026 | K40: 6 oct. 2026 | L40: Notebook 01_etl, exécuté sur les ventes complètes
A41: T040 | B41: US09 | C41: E2 Intégration et modélisation (ETL) | D41: Sprint 1 | E41: Concaténer les trimestres avec une colonne source (année, trimestre) | F41: Python (pandas) | G41: 1 | H41: Yacine | I41: Terminé | J41: 18 oct. 2026 | K41: 6 oct. 2026 | L41: Notebook 01_etl, exécuté sur les ventes complètes
A42: T041 | B42: US09 | C42: E2 Intégration et modélisation (ETL) | D42: Sprint 1 | E42: Contrôler les doublons d'IdVente entre trimestres | F42: Python (pandas) | G42: 1.5 | H42: Barnabé | I42: Terminé | J42: 18 oct. 2026 | K42: 6 oct. 2026 | L42: Notebook 01_etl, exécuté sur les ventes complètes
A43: T042 | B43: US09 | C43: E2 Intégration et modélisation (ETL) | D43: Sprint 1 | E43: Réconcilier lignes et totaux (ventes, coûts, retours) avant et après consolidation | F43: Python (pandas) | G43: 2 | H43: Barnabé | I43: Terminé | J43: 18 oct. 2026 | K43: 6 oct. 2026 | L43: Notebook 01_etl, exécuté sur les ventes complètes
A44: T043 | B44: US10 | C44: E2 Intégration et modélisation (ETL) | D44: Sprint 1 | E44: Concevoir le schéma en flocon (faits ventes, boutique → géographie, produit → sous-catégorie → catégorie, promotion, date, canal, devise) | F44: draw.io / Power BI | G44: 2 | H44: Mouncif | I44: Terminé | J44: 18 oct. 2026 | K44: 6 oct. 2026 | L44: Notebook 02_flocon, exécuté sur les ventes complètes
A45: T044 | B45: US10 | C45: E2 Intégration et modélisation (ETL) | D45: Sprint 1 | E45: Réaligner les dates des dimensions sur nos données (+12 ans : promotions, ouverture et fermeture des boutiques, produits) | F45: Python (pandas) | G45: 1 | H45: Mouncif | I45: Terminé | J45: 18 oct. 2026 | K45: 6 oct. 2026 | L45: Notebook 02_flocon, exécuté sur les ventes complètes
A46: T045 | B46: US10 | C46: E2 Intégration et modélisation (ETL) | D46: Sprint 1 | E46: Joindre le canal et la devise récupérés depuis FactSales | F46: Python (pandas) | G46: 1 | H46: Mouncif | I46: Terminé | J46: 18 oct. 2026 | K46: 6 oct. 2026 | L46: Notebook 02_flocon, exécuté sur les ventes complètes
A47: T046 | B47: US10 | C47: E2 Intégration et modélisation (ETL) | D47: Sprint 1 | E47: Construire la dimension date (jour, semaine, mois, trimestre, jour férié, période COVID) | F47: Python (pandas) | G47: 2 | H47: Yacine | I47: Terminé | J47: 18 oct. 2026 | K47: 6 oct. 2026 | L47: Notebook 02_flocon, exécuté sur les ventes complètes
A48: T047 | B48: US10 | C48: E2 Intégration et modélisation (ETL) | D48: Sprint 1 | E48: Aplatir la hiérarchie produit (produit, sous-catégorie, catégorie) et géographie (ville, région, pays) | F48: Python (pandas) | G48: 2 | H48: Yacine | I48: Terminé | J48: 18 oct. 2026 | K48: 6 oct. 2026 | L48: Notebook 02_flocon, exécuté sur les ventes complètes
A49: T048 | B49: US10 | C49: E2 Intégration et modélisation (ETL) | D49: Sprint 1 | E49: Joindre les dimensions à la table de faits et mesurer le taux de correspondance | F49: Python (pandas) | G49: 2 | H49: Mouncif | I49: Terminé | J49: 18 oct. 2026 | K49: 6 oct. 2026 | L49: Notebook 02_flocon, exécuté sur les ventes complètes
A50: T049 | B50: US10 | C50: E2 Intégration et modélisation (ETL) | D50: Sprint 1 | E50: Traiter les clés sans correspondance (membre « Inconnu ») et documenter | F50: Python (pandas) | G50: 1.5 | H50: Mouncif | I50: Terminé | J50: 18 oct. 2026 | K50: 6 oct. 2026 | L50: Notebook 02_flocon, exécuté sur les ventes complètes
A51: T050 | B51: US10 | C51: E2 Intégration et modélisation (ETL) | D51: Sprint 1 | E51: Exporter les tables consolidées et jointes dans data/interim (Parquet et CSV) | F51: Python (pandas) | G51: 1 | H51: Mouncif | I51: Terminé | J51: 18 oct. 2026 | K51: 6 oct. 2026 | L51: Notebook 02_flocon, exécuté sur les ventes complètes
A52: T051 | B52: US11 | C52: E2 Intégration et modélisation (ETL) | D52: Sprint 1 | E52: Factoriser le code partagé dans src/ (config, etl, qualite, features, modeles, viz) | F52: Python | G52: 3 | H52: À répartir | I52: En cours | J52: 18 oct. 2026 | L52: config, etl, viz et analyse existent ; les autres modules restent à créer (à confirmer)
A53: T052 | B53: US11 | C53: E2 Intégration et modélisation (ETL) | D53: Sprint 1 | E53: Écrire run_pipeline.py (papermill : ordre des dépendances, exécution parallèle des notebooks indépendants, copies exécutées) | F53: Python (papermill) | G53: 3 | H53: À répartir | I53: À faire | J53: 18 oct. 2026
A54: T053 | B54: US11 | C54: E2 Intégration et modélisation (ETL) | D54: Sprint 1 | E54: Tester l'exécution complète sur un poste vierge | F54: Python | G54: 1 | H54: À répartir | I54: À faire | J54: 18 oct. 2026
A55: T054 | B55: US11 | C55: E2 Intégration et modélisation (ETL) | D55: Sprint 1 | E55: Rédiger le README d'exécution du pipeline | F55: GitHub | G55: 1 | H55: À répartir | I55: À faire | J55: 18 oct. 2026
A56: T055 | B56: US11 | C56: E2 Intégration et modélisation (ETL) | D56: Sprint 1 | E56: Revue de code croisée du pipeline | F56: GitHub | G56: 1.5 | H56: Barnabé | I56: À faire | J56: 18 oct. 2026
A57: T056 | B57: US27 | C57: E0 Gestion de projet Scrum | D57: Sprint 1 | E57: Sprint 1 : planification, revue et rétrospective | F57: Réunion | G57: 2 | H57: Achraf | I57: À faire | J57: 18 oct. 2026
A58: T057 | B58: US12 | C58: E3 Qualité et nettoyage | D58: Sprint 2 | E58: Mesurer le taux de valeurs manquantes par variable | F58: Python (pandas) | G58: 1 | H58: Yacine | I58: Terminé | J58: 1 nov. 2026 | K58: 6 oct. 2026 | L58: Notebook 03_diagnostic, exécuté sur les ventes complètes
A59: T058 | B59: US12 | C59: E3 Qualité et nettoyage | D59: Sprint 2 | E59: Détecter les valeurs nulles ou négatives (quantités, prix, coûts, montants) | F59: Python (pandas) | G59: 1.5 | H59: Yacine | I59: Terminé | J59: 1 nov. 2026 | K59: 6 oct. 2026 | L59: Notebook 03_diagnostic, exécuté sur les ventes complètes
A60: T059 | B60: US12 | C60: E3 Qualité et nettoyage | D60: Sprint 2 | E60: Contrôler : Montant des ventes = Prix unitaire × Quantité − Remise | F60: Python (pandas) | G60: 1.5 | H60: Barnabé | I60: Terminé | J60: 1 nov. 2026 | K60: 6 oct. 2026 | L60: Notebook 03_diagnostic, exécuté sur les ventes complètes
A61: T060 | B61: US12 | C61: E3 Qualité et nettoyage | D61: Sprint 2 | E61: Contrôler : Coût total = Coût unitaire × Quantité | F61: Python (pandas) | G61: 1 | H61: Barnabé | I61: Terminé | J61: 1 nov. 2026 | K61: 6 oct. 2026 | L61: Notebook 03_diagnostic, exécuté sur les ventes complètes
A62: T061 | B62: US12 | C62: E3 Qualité et nettoyage | D62: Sprint 2 | E62: Contrôler : quantités et montants de retour inférieurs ou égaux aux ventes | F62: Python (pandas) | G62: 1 | H62: Yacine | I62: Terminé | J62: 1 nov. 2026 | K62: 6 oct. 2026 | L62: Notebook 03_diagnostic, exécuté sur les ventes complètes
A63: T062 | B63: US12 | C63: E3 Qualité et nettoyage | D63: Sprint 2 | E63: Contrôler : Quantité de remise inférieure ou égale à la Quantité de vente | F63: Python (pandas) | G63: 1 | H63: Yacine | I63: Terminé | J63: 1 nov. 2026 | K63: 6 oct. 2026 | L63: Notebook 03_diagnostic, exécuté sur les ventes complètes
A64: T063 | B64: US12 | C64: E3 Qualité et nettoyage | D64: Sprint 2 | E64: Contrôler la cohérence promotion et remise (promo sans remise, remise sans promo) | F64: Python (pandas) | G64: 1.5 | H64: Yacine | I64: Terminé | J64: 1 nov. 2026 | K64: 6 oct. 2026 | L64: Notebook 03_diagnostic, exécuté sur les ventes complètes
A65: T064 | B65: US12 | C65: E3 Qualité et nettoyage | D65: Sprint 2 | E65: Contrôler les ventes hors dates de promotion ou pendant la fermeture d'une boutique | F65: Python (pandas) | G65: 1.5 | H65: Yacine | I65: Terminé | J65: 1 nov. 2026 | K65: 6 oct. 2026 | L65: Notebook 03_diagnostic, exécuté sur les ventes complètes
A66: T065 | B66: US12 | C66: E3 Qualité et nettoyage | D66: Sprint 2 | E66: Comparer prix et coûts unitaires des transactions avec ceux de DimProduct | F66: Python (pandas) | G66: 1.5 | H66: Barnabé | I66: Terminé | J66: 1 nov. 2026 | K66: 6 oct. 2026 | L66: Notebook 03_diagnostic, exécuté sur les ventes complètes
A67: T066 | B67: US12 | C67: E3 Qualité et nettoyage | D67: Sprint 2 | E67: Détecter les valeurs aberrantes (IQR, z-score) et les visualiser | F67: Python (seaborn) | G67: 2 | H67: Yacine | I67: Terminé | J67: 1 nov. 2026 | K67: 6 oct. 2026 | L67: Notebook 03_diagnostic, exécuté sur les ventes complètes
A68: T067 | B68: US12 | C68: E3 Qualité et nettoyage | D68: Sprint 2 | E68: Rédiger la synthèse chiffrée des anomalies | F68: Word | G68: 2 | H68: Yacine | I68: En revue | J68: 1 nov. 2026 | L68: Repris dans le rapport L3 (sections 2 et 3), première version du 7 oct. 2026
A69: T068 | B69: US13 | C69: E3 Qualité et nettoyage | D69: Sprint 2 | E69: Définir et faire valider les règles de traitement (supprimer, corriger, imputer, signaler) | F69: Réunion | G69: 1.5 | H69: Yacine | I69: Terminé | J69: 1 nov. 2026 | K69: 6 oct. 2026 | L69: Notebook 04_nettoyage (règles N1 à N6, journal de nettoyage)
A70: T069 | B70: US13 | C70: E3 Qualité et nettoyage | D70: Sprint 2 | E70: Appliquer les règles de nettoyage dans le pipeline (data/interim → data/clean) | F70: Python (pandas) | G70: 3 | H70: Mouncif | I70: Terminé | J70: 1 nov. 2026 | K70: 6 oct. 2026 | L70: Notebook 04_nettoyage (règles N1 à N6, journal de nettoyage)
A71: T070 | B71: US13 | C71: E3 Qualité et nettoyage | D71: Sprint 2 | E71: Produire le journal de nettoyage (avant et après, lignes touchées) | F71: Python (pandas) | G71: 1.5 | H71: Mouncif | I71: Terminé | J71: 1 nov. 2026 | K71: 6 oct. 2026 | L71: Notebook 04_nettoyage (règles N1 à N6, journal de nettoyage)
A72: T071 | B72: US13 | C72: E3 Qualité et nettoyage | D72: Sprint 2 | E72: Écrire des tests de qualité automatisés (assertions) | F72: Python (pytest) | G72: 2 | H72: Mouncif | I72: À faire | J72: 1 nov. 2026
A73: T072 | B73: US27 | C73: E0 Gestion de projet Scrum | D73: Sprint 2 | E73: Sprint 2 : planification, revue et rétrospective | F73: Réunion | G73: 2 | H73: Achraf | I73: À faire | J73: 1 nov. 2026
A74: T073 | B74: US14 | C74: E4 Transformation et variables dérivées | D74: Sprint 3 | E74: Calculer la marge brute en valeur (Montant des ventes − Coût total) | F74: Python (pandas) | G74: 1 | H74: Yacine | I74: Terminé | J74: 8 nov. 2026 | K74: 6 oct. 2026 | L74: Notebook 05_variables
A75: T074 | B75: US14 | C75: E4 Transformation et variables dérivées | D75: Sprint 3 | E75: Calculer les ventes nettes (Montant des ventes − Montant du retour) et la marge après retours (hypothèse documentée) | F75: Python (pandas) | G75: 1.5 | H75: Yacine | I75: Terminé | J75: 8 nov. 2026 | K75: 6 oct. 2026 | L75: Notebook 05_variables
A76: T075 | B76: US14 | C76: E4 Transformation et variables dérivées | D76: Sprint 3 | E76: Calculer le taux de retour (Quantité de retour / Quantité de vente) | F76: Python (pandas) | G76: 0.5 | H76: Barnabé | I76: Terminé | J76: 8 nov. 2026 | K76: 6 oct. 2026 | L76: Notebook 05_variables
A77: T076 | B77: US14 | C77: E4 Transformation et variables dérivées | D77: Sprint 3 | E77: Calculer le taux de remise effectif et les tranches de remise | F77: Python (pandas) | G77: 1 | H77: Barnabé | I77: Terminé | J77: 8 nov. 2026 | K77: 6 oct. 2026 | L77: Notebook 05_variables
A78: T077 | B78: US14 | C78: E4 Transformation et variables dérivées | D78: Sprint 3 | E78: Créer l'indicateur promotion et les variables issues de DimPromotion (type, catégorie, % annoncé) | F78: Python (pandas) | G78: 1 | H78: Barnabé | I78: Terminé | J78: 8 nov. 2026 | K78: 6 oct. 2026 | L78: Notebook 05_variables
A79: T078 | B79: US14 | C79: E4 Transformation et variables dérivées | D79: Sprint 3 | E79: Mettre à jour le dictionnaire de données avec les variables dérivées | F79: Excel | G79: 1 | H79: Mouncif | I79: À faire | J79: 8 nov. 2026
A80: T079 | B80: US15 | C80: E4 Transformation et variables dérivées | D80: Sprint 3 | E80: Construire les agrégats par boutique, produit, promotion et période (data/clean/agregats) | F80: Python (pandas) | G80: 2 | H80: Yacine | I80: Terminé | J80: 8 nov. 2026 | K80: 6 oct. 2026 | L80: Notebook 05_variables (dossier data/clean/agregats)
A81: T080 | B81: US15 | C81: E4 Transformation et variables dérivées | D81: Sprint 3 | E81: Construire les séries hebdomadaires pour la prévision | F81: Python (pandas) | G81: 1.5 | H81: Yacine | I81: Terminé | J81: 8 nov. 2026 | K81: 6 oct. 2026 | L81: Notebook 05_variables (dossier data/clean/agregats)
A82: T081 | B82: US15 | C82: E4 Transformation et variables dérivées | D82: Sprint 3 | E82: Standardiser les indicateurs de comparaison (par transaction, par jour de promotion, par m²) | F82: Python (pandas) | G82: 1.5 | H82: À répartir | I82: À faire | J82: 8 nov. 2026
A83: T082 | B83: US16 | C83: E8 Documentation et livrables | D83: Sprint 3 | E83: Rédiger : sources, collecte et modèle de données | F83: Word | G83: 2 | H83: Toute l'équipe | I83: En revue | J83: 8 nov. 2026 | L83: Première version rédigée le 7 oct. 2026 (L3_diagnostic_nettoyage_transformation.docx), à relire par l'équipe
A84: T083 | B84: US16 | C84: E8 Documentation et livrables | D84: Sprint 3 | E84: Rédiger : diagnostic, règles de nettoyage et transformations | F84: Word | G84: 3 | H84: Toute l'équipe | I84: En revue | J84: 8 nov. 2026 | L84: Première version rédigée le 7 oct. 2026 (L3_diagnostic_nettoyage_transformation.docx), à relire par l'équipe
A85: T084 | B85: US16 | C85: E8 Documentation et livrables | D85: Sprint 3 | E85: Rédiger : limites et hypothèses | F85: Word | G85: 1.5 | H85: Toute l'équipe | I85: En revue | J85: 8 nov. 2026 | L85: Première version rédigée le 7 oct. 2026 (L3_diagnostic_nettoyage_transformation.docx), à relire par l'équipe
A86: T085 | B86: US16 | C86: E8 Documentation et livrables | D86: Sprint 3 | E86: Produire les visuels de qualité des données | F86: Python (matplotlib) | G86: 2 | H86: Mouncif | I86: Terminé | J86: 8 nov. 2026 | K86: 6 oct. 2026 | L86: Figures du notebook 03_diagnostic
A87: T086 | B87: US16 | C87: E8 Documentation et livrables | D87: Sprint 3 | E87: Relecture croisée, mise en page et remise (9 nov.) | F87: Word | G87: 1.5 | H87: Yacine | I87: À faire | J87: 8 nov. 2026 | L87: Reste à faire : relecture croisée, nom du cours et du professeur sur la page de garde, figures de la machine de l'équipe
A88: T087 | B88: US27 | C88: E0 Gestion de projet Scrum | D88: Sprint 3 | E88: Sprint 3 : planification, revue et rétrospective | F88: Réunion | G88: 1.5 | H88: Achraf | I88: À faire | J88: 8 nov. 2026
A89: T088 | B89: US17 | C89: E5 Analyse exploratoire (Q1 à Q5) | D89: Sprint 4 | E89: Chiffre d'affaires et marge en valeur par boutique, type de boutique et pays | F89: Python (pandas, plotly) | G89: 2 | H89: Yacine | I89: Terminé | J89: 22 nov. 2026 | K89: 6 oct. 2026 | L89: Notebook 06_q1_performance
A90: T089 | B90: US17 | C90: E5 Analyse exploratoire (Q1 à Q5) | D90: Sprint 4 | E90: Ventes par surface et par employé (productivité des boutiques) | F90: Python (pandas) | G90: 1.5 | H90: Yacine | I90: Terminé | J90: 22 nov. 2026 | K90: 6 oct. 2026 | L90: Notebook 06_q1_performance : surface et effectif sans lien avec les ventes (corrélations, section 6)
A91: T090 | B91: US17 | C91: E5 Analyse exploratoire (Q1 à Q5) | D91: Sprint 4 | E91: Chiffre d'affaires et marge par catégorie, sous-catégorie et marque | F91: Python (pandas, seaborn) | G91: 2 | H91: Barnabé | I91: Terminé | J91: 22 nov. 2026 | K91: 6 oct. 2026 | L91: Notebook 06_q1_performance
A92: T091 | B92: US17 | C92: E5 Analyse exploratoire (Q1 à Q5) | D92: Sprint 4 | E92: Analyse de Pareto (80/20) des produits et des boutiques | F92: Python (matplotlib) | G92: 1.5 | H92: Barnabé | I92: Terminé | J92: 22 nov. 2026 | K92: 6 oct. 2026 | L92: Notebook 06_q1_performance
A93: T092 | B93: US17 | C93: E5 Analyse exploratoire (Q1 à Q5) | D93: Sprint 4 | E93: Tendances, saisonnalité et effet COVID-19 | F93: Python (statsmodels) | G93: 2.5 | H93: Barnabé | I93: Terminé | J93: 22 nov. 2026 | K93: 6 oct. 2026 | L93: Notebook 06_q1_performance
A94: T093 | B94: US17 | C94: E5 Analyse exploratoire (Q1 à Q5) | D94: Sprint 4 | E94: Décomposition de la variance ou ANOVA des facteurs boutique, produit, promotion | F94: Python (scipy, statsmodels) | G94: 2.5 | H94: Barnabé | I94: Terminé | J94: 22 nov. 2026 | K94: 6 oct. 2026 | L94: Notebook 06_q1_performance
A95: T094 | B95: US17 | C95: E5 Analyse exploratoire (Q1 à Q5) | D95: Sprint 4 | E95: Rédiger la synthèse Q1 | F95: Word | G95: 1 | H95: Yacine et Barnabé | I95: Terminé | J95: 22 nov. 2026 | K95: 6 oct. 2026 | L95: Synthèse rédigée dans le notebook 06 ; à reprendre dans le rapport L4 (T150)
A96: T095 | B96: US18 | C96: E5 Analyse exploratoire (Q1 à Q5) | D96: Sprint 4 | E96: Comparer volume, panier et marge en valeur, promo et hors promo | F96: Python (pandas) | G96: 2 | H96: Yacine | I96: Terminé | J96: 22 nov. 2026 | K96: 6 oct. 2026 | L96: Notebook 07_q2_promotions (3 angles, 11 tests)
A97: T096 | B97: US18 | C97: E5 Analyse exploratoire (Q1 à Q5) | D97: Sprint 4 | E97: Comparer par type et catégorie de promotion | F97: Python (pandas, seaborn) | G97: 2 | H97: Yacine | I97: Terminé | J97: 22 nov. 2026 | K97: 6 oct. 2026 | L97: Notebook 07_q2_promotions (3 angles, 11 tests)
A98: T097 | B98: US18 | C98: E5 Analyse exploratoire (Q1 à Q5) | D98: Sprint 4 | E98: Mesurer l'effet avant, pendant et après chaque promotion (uplift) | F98: Python (pandas) | G98: 2.5 | H98: Yacine | I98: Terminé | J98: 22 nov. 2026 | K98: 6 oct. 2026 | L98: Notebook 07_q2_promotions (3 angles, 11 tests)
A99: T098 | B99: US18 | C99: E5 Analyse exploratoire (Q1 à Q5) | D99: Sprint 4 | E99: Tester statistiquement les écarts (Mann-Whitney, Kruskal-Wallis) | F99: Python (scipy) | G99: 1.5 | H99: Yacine | I99: Terminé | J99: 22 nov. 2026 | K99: 6 oct. 2026 | L99: Notebook 07_q2_promotions (3 angles, 11 tests)
A100: T099 | B100: US18 | C100: E5 Analyse exploratoire (Q1 à Q5) | D100: Sprint 4 | E100: Rédiger la synthèse Q2 | F100: Word | G100: 1 | H100: Yacine | I100: Terminé | J100: 22 nov. 2026 | K100: 6 oct. 2026 | L100: Synthèse rédigée dans le notebook 07 ; à reprendre dans le rapport L4 (T150)
... A110: T109 | B110: US28 | C110: E6 Modélisation prédictive | D110: Sprint 4 | E110: Évaluer les modèles (AUC, précision, rappel) sur une période de test | F110: Python (scikit-learn) | G110: 1.5 | H110: Yacine | I110: Terminé | J110: 22 nov. 2026 | K110: 6 oct. 2026 | L110: Notebook 08_q3_q4_retours, section 7
A111: T110 | B111: US28 | C111: E6 Modélisation prédictive | D111: Sprint 4 | E111: Interpréter les facteurs de retour (importance des variables, SHAP) | F111: Python (shap) | G111: 2 | H111: Yacine | I111: Écartée | J111: 22 nov. 2026 | L111: Sans objet : le modèle ne prédit pas mieux que le hasard (AUC de 0,57)
A112: T111 | B112: US20 | C112: E7 Tableaux de bord | D112: Sprint 4 | E112: Concevoir la maquette du tableau de bord Excel (indicateurs clés, graphiques) | F112: Excel | G112: 1.5 | H112: Barnabé | I112: À faire | J112: 22 nov. 2026
A113: T112 | B113: US20 | C113: E7 Tableaux de bord | D113: Sprint 4 | E113: Importer les données agrégées avec Power Query | F113: Excel (Power Query) | G113: 1.5 | H113: Barnabé | I113: À faire | J113: 22 nov. 2026
A114: T113 | B114: US20 | C114: E7 Tableaux de bord | D114: Sprint 4 | E114: Construire tableaux croisés dynamiques et graphiques | F114: Excel | G114: 3 | H114: Barnabé | I114: À faire | J114: 22 nov. 2026
A115: T114 | B115: US20 | C115: E7 Tableaux de bord | D115: Sprint 4 | E115: Ajouter segments et chronologie (boutique, catégorie, période, promotion) | F115: Excel | G115: 1.5 | H115: Barnabé | I115: À faire | J115: 22 nov. 2026
A116: T115 | B116: US20 | C116: E7 Tableaux de bord | D116: Sprint 4 | E116: Mettre en forme et faire tester par un autre membre | F116: Excel | G116: 1.5 | H116: Barnabé | I116: À faire | J116: 22 nov. 2026
A117: T116 | B117: US27 | C117: E0 Gestion de projet Scrum | D117: Sprint 4 | E117: Sprint 4 : planification, revue et rétrospective | F117: Réunion | G117: 2 | H117: Achraf | I117: À faire | J117: 22 nov. 2026
A118: T117 | B118: US22 | C118: E5 Analyse exploratoire (Q1 à Q5) | D118: Sprint 5 | E118: Marge en valeur par tranche de remise et par catégorie | F118: Python (pandas) | G118: 2 | H118: Barnabé | I118: Terminé | J118: 6 déc. 2026 | K118: 7 oct. 2026 | L118: Notebook 09_q5_remises, sections 2 et 7
A119: T118 | B119: US22 | C119: E5 Analyse exploratoire (Q1 à Q5) | D119: Sprint 5 | E119: Estimer l'élasticité descriptive du volume à la remise | F119: Python (statsmodels) | G119: 2.5 | H119: Barnabé | I119: Terminé | J119: 6 déc. 2026 | K119: 7 oct. 2026 | L119: Notebook 09 : supplément d'unités d'une ligne remisée, par niveau et par type de boutique (sections 4 à 6)
A120: T119 | B120: US22 | C120: E5 Analyse exploratoire (Q1 à Q5) | D120: Sprint 5 | E120: Identifier les seuils de remise où la marge en valeur baisse ou les retours augmentent | F120: Python (pandas) | G120: 2 | H120: Barnabé | I120: Terminé | J120: 6 déc. 2026 | K120: 7 oct. 2026 | L120: Seuils de rentabilité dans 07 (section 9), bornes de chaque décision dans 09 (section 8)
A121: T120 | B121: US22 | C121: E5 Analyse exploratoire (Q1 à Q5) | D121: Sprint 5 | E121: Rédiger la synthèse Q5 et les pistes de recommandations | F121: Word | G121: 1.5 | H121: Barnabé | I121: Terminé | J121: 6 déc. 2026 | K121: 7 oct. 2026 | L121: Synthèse rédigée dans le notebook 09 ; à reprendre dans le rapport L4 (T150)
A122: T121 | B122: US23 | C122: E6 Modélisation prédictive | D122: Sprint 5 | E122: Définir la cible et la granularité de prévision (ventes mensuelles par catégorie et par année de lancement des produits) | F122: Réunion | G122: 1 | H122: À répartir | I122: À faire | J122: 6 déc. 2026 | L122: Libellé modifié le 7 oct. 2026 : prévision par l'âge du catalogue
A123: T122 | B123: US23 | C123: E6 Modélisation prédictive | D123: Sprint 5 | E123: Découpage temporel entraînement et test | F123: Python (scikit-learn) | G123: 1 | H123: À répartir | I123: À faire | J123: 6 déc. 2026
A124: T123 | B124: US23 | C124: E6 Modélisation prédictive | D124: Sprint 5 | E124: Modèle de référence naïf saisonnier | F124: Python | G124: 1 | H124: À répartir | I124: À faire | J124: 6 déc. 2026
A125: T124 | B125: US23 | C125: E6 Modélisation prédictive | D125: Sprint 5 | E125: Modèle SARIMA | F125: Python (statsmodels) | G125: 3 | H125: Yacine | I125: Écartée | J125: 6 déc. 2026 | L125: 24 mois de données : deux cycles saisonniers seulement, insuffisant pour un modèle SARIMA
A126: T125 | B126: US23 | C126: E6 Modélisation prédictive | D126: Sprint 5 | E126: Modèle de gradient boosting avec variables de calendrier et d'âge du produit | F126: Python (scikit-learn) | G126: 3 | H126: À répartir | I126: À faire | J126: 6 déc. 2026 | L126: Libellé modifié le 7 oct. 2026 : la promotion n'est plus une variable explicative
A127: T126 | B127: US23 | C127: E6 Modélisation prédictive | D127: Sprint 5 | E127: Évaluer et comparer les modèles (MAE, MAPE) | F127: Python (scikit-learn) | G127: 1.5 | H127: À répartir | I127: À faire | J127: 6 déc. 2026
A128: T127 | B128: US23 | C128: E6 Modélisation prédictive | D128: Sprint 5 | E128: Interpréter les résultats (importance des variables) | F128: Python | G128: 1.5 | H128: À répartir | I128: À faire | J128: 6 déc. 2026
A129: T128 | B129: US23 | C129: E6 Modélisation prédictive | D129: Sprint 5 | E129: Exporter les prévisions de ventes vers data/outputs/predictions | F129: Python (pandas) | G129: 0.5 | H129: À répartir | I129: À faire | J129: 6 déc. 2026 | L129: Libellé modifié le 7 oct. 2026 : plus de risque de retour par vente (US28)
A130: T129 | B130: US29 | C130: E6 Modélisation prédictive | D130: Sprint 5 | E130: Construire la table d'apprentissage (catégorie × boutique × semaine : remise, volume, marge, retours) | F130: Python (pandas) | G130: 2 | H130: Barnabé | I130: Écartée | J130: 6 déc. 2026 | L130: US29 abandonnée : promotions générales et calées sur le calendrier, aucun groupe témoin (07 et 09)
A131: T130 | B131: US29 | C131: E6 Modélisation prédictive | D131: Sprint 5 | E131: Modéliser le volume en fonction du taux de remise (régression log-log, gradient boosting) | F131: Python (statsmodels, scikit-learn) | G131: 3 | H131: Barnabé | I131: Écartée | J131: 6 déc. 2026 | L131: US29 abandonnée : promotions générales et calées sur le calendrier, aucun groupe témoin (07 et 09)
A132: T131 | B132: US29 | C132: E6 Modélisation prédictive | D132: Sprint 5 | E132: Estimer l'uplift incrémental par type de promotion (groupe de contrôle hors promo comparable) | F132: Python (pandas) | G132: 2.5 | H132: Barnabé | I132: Écartée | J132: 6 déc. 2026 | L132: US29 abandonnée : promotions générales et calées sur le calendrier, aucun groupe témoin (07 et 09)
A133: T132 | B133: US29 | C133: E6 Modélisation prédictive | D133: Sprint 5 | E133: Valider le modèle de réponse sur une période de test | F133: Python (scikit-learn) | G133: 1.5 | H133: Barnabé | I133: Écartée | J133: 6 déc. 2026 | L133: US29 abandonnée : promotions générales et calées sur le calendrier, aucun groupe témoin (07 et 09)
...

Sheet Changements
A1: Date | B1: Élément | C1: Changement | D1: Raison | E1: Statut dans Jira
A2: 6 oct. 2026 | B2: Périmètre des données | C2: Passage des fichiers fournis (5 catégories, trimestres 1 à 3, 144 874 lignes) aux ventes complètes des 56 boutiques (8 catégories, 8 trimestres, 376 234 lignes) | D2: Seul périmètre comparable aux charges du plan stratégique ; les catégories absentes pèsent plus de la moitié du chiffre d'affaires ; fin d'année et promotion des Fêtes présentes | E2: Sans objet
A3: 6 oct. 2026 | B3: US34 (nouvelle, Must) | C3: Étendre les ventes au périmètre complet : 8 tâches T167 à T174, dont 7 déjà terminées | D3: Travail réalisé le 6 octobre, à tracer dans le backlog | E3: À créer
A4: 6 oct. 2026 | B4: US35 (nouvelle, Should) | C4: Rentabilité nette par boutique à partir des charges du plan stratégique : 5 tâches T175 à T179 | D4: Les charges par boutique existent dans Contoso et se rapprochent de nos ventes au cent près | E4: À créer
A5: 6 oct. 2026 | B5: US36 (nouvelle, Should) | C5: Dépenses de publicité face aux promotions : 3 tâches T180 à T182 | D5: Complète Q2 et Q5 | E5: À créer
A6: 6 oct. 2026 | B6: US37 (nouvelle, Could) | C6: Détail des ventes en ligne pour comprendre les remises : 3 tâches T183 à T185 | D6: Seule table transactionnelle de la base, limitée au canal en ligne | E6: À créer
A7: 6 oct. 2026 | B7: US28 | C7: Priorité Must -> Could (modèle prédictif du risque de retour) | D7: L'énoncé demande d'identifier les déterminants des retours (US19, US21) et des modèles prédictifs de ventes (US23), pas un modèle prédictif des retours | E7: À modifier
A8: 6 oct. 2026 | B8: US30 | C8: Priorité Must -> Could (simulation de scénarios what-if) | D8: La stratégie d'optimisation demandée est couverte par US31 | E8: À modifier
A9: 6 oct. 2026 | B9: US32 | C9: Priorité Must -> Could (analyse de sensibilité et calendrier promotionnel) | D9: Les recommandations opérationnelles demandées sont couvertes par US26 | E9: À modifier
A10: 6 oct. 2026 | B10: US09 | C10: Libellé : « tous les trimestres de ventes (6 fournis, puis 8) » | D10: Suite du changement de périmètre | E10: À modifier
A11: 6 oct. 2026 | B11: Nettoyage | C11: Nouvelle règle N6 : quantité remisée ramenée à la quantité vendue sur 386 lignes. Aucun montant modifié : le chiffre d'affaires reste égal à celui du plan stratégique | D11: Anomalie apparue avec la catégorie Home Appliances ; démarche détaillée dans 03_diagnostic et dans le L3 | E11: Sans objet
A12: 7 oct. 2026 | B12: Orientation du projet | C12: Les deux premiers leviers de rentabilité sont le renouvellement du catalogue et la maîtrise des charges, et non les promotions et les retours. Les sprints 5 et 6 sont réorientés en conséquence. | D12: Résultats des notebooks 06 à 09 : catalogue en place −152 M$ en 2021, charges en hausse pendant que les ventes baissent, promotions sans effet mesuré sur les ventes, retours uniformes et peu coûteux | E12: Sans objet
... A29: 7 oct. 2026 | B29: US16 (livrable 3) | C29: Première version du rapport rédigée : T067, T082, T083 et T084 passent à « En revue » | D29: Rédaction en avance sur le sprint 3. Reste la relecture par l'équipe (T086) | E29: À modifier
A31: Les documents remis le 5 octobre (L1, L2, présentation UA1) ne sont pas modifiés : cet onglet et le L3 expliquent les changements.
